evidence_seeker/__about__.py
evidence_seeker/__init__.py
evidence_seeker/backend.py
evidence_seeker/datamodels.py
evidence_seeker/evidence_seeker.py
evidence_seeker/results.py
evidence_seeker/utils.py
evidence_seeker/cli/__init__.py
evidence_seeker/cli/config.py
evidence_seeker/cli/evse_cli.py
evidence_seeker/confirmation_aggregation/__init__.py
evidence_seeker/confirmation_aggregation/base.py
evidence_seeker/confirmation_aggregation/config.py
evidence_seeker/confirmation_analysis/__init__.py
evidence_seeker/confirmation_analysis/base.py
evidence_seeker/confirmation_analysis/config.py
evidence_seeker/confirmation_analysis/workflows.py
evidence_seeker/demo_app/__init__.py
evidence_seeker/demo_app/app.py
evidence_seeker/demo_app/app_config.py
evidence_seeker/package_data/__init__.py
evidence_seeker/package_data/config/api_keys.txt
evidence_seeker/package_data/config/confirmation_analysis_config.yaml
evidence_seeker/package_data/config/demo_app_config.yaml
evidence_seeker/package_data/config/preprocessing_config.yaml
evidence_seeker/package_data/config/retrieval_config.yaml
evidence_seeker/package_data/templates/default_markdown.tmpl
evidence_seeker/preprocessing/__init__.py
evidence_seeker/preprocessing/base.py
evidence_seeker/preprocessing/config.py
evidence_seeker/preprocessing/simple_preprocessing_workflow_deprecated.py
evidence_seeker/preprocessing/workflows.py
evidence_seeker/retrieval/__init__.py
evidence_seeker/retrieval/base.py
evidence_seeker/retrieval/config.py
evidence_seeker/retrieval/document_retriever.py
evidence_seeker/retrieval/index_builder.py
evidence_seeker-0.1.2.dist-info/METADATA
evidence_seeker-0.1.2.dist-info/WHEEL
evidence_seeker-0.1.2.dist-info/entry_points.txt
evidence_seeker-0.1.2.dist-info/licenses/LICENSE
evidence_seeker-0.1.2.dist-info/RECORD
